ephemeris_mcp/__init__.py
ephemeris_mcp/engine.py
ephemeris_mcp/logging_config.py
ephemeris_mcp/server.py
ephemeris_mcp-1.1.1.dist-info/METADATA
ephemeris_mcp-1.1.1.dist-info/WHEEL
ephemeris_mcp-1.1.1.dist-info/entry_points.txt
ephemeris_mcp-1.1.1.dist-info/RECORD
