Metadata-Version: 2.4
Name: ephemeris-mcp
Version: 1.1.1
Summary: Precision astronomical ephemeris calculations via Model Context Protocol (MCP). Provides planetary positions using Swiss Ephemeris.
Project-URL: Homepage, https://github.com/scottchronicity/ephemeris-mcp
Project-URL: Documentation, https://github.com/scottchronicity/ephemeris-mcp#readme
Project-URL: Repository, https://github.com/scottchronicity/ephemeris-mcp
Project-URL: Issues, https://github.com/scottchronicity/ephemeris-mcp/issues
Author-email: Scott Carroll <scott@rippleroot.studios>
License: MIT
Keywords: ai,astrology,ephemeris,llm,mcp,model-context-protocol
Classifier: Development Status :: 3 - Alpha
Classifier: Intended Audience :: Developers
Classifier: License :: OSI Approved :: MIT License
Classifier: Programming Language :: Python :: 3
Classifier: Programming Language :: Python :: 3.10
Classifier: Programming Language :: Python :: 3.11
Classifier: Topic :: Scientific/Engineering :: Astronomy
Classifier: Topic :: Software Development :: Libraries :: Python Modules
Requires-Python: <3.12,>=3.10
Requires-Dist: flatlib
Requires-Dist: mcp>=0.1.0
Requires-Dist: pydantic
Requires-Dist: structlog>=24.0.0
Provides-Extra: dev
Requires-Dist: pytest-cov>=4.1.0; extra == 'dev'
Requires-Dist: pytest>=8.0.0; extra == 'dev'
Requires-Dist: python-semantic-release>=9.0.0; extra == 'dev'
Requires-Dist: ruff>=0.8.0; extra == 'dev'
